<Properties StartupConfiguration="{D2A622E2-8ED2-853C-E7EB-A98D429F43BE}|">
  <MonoDevelop.Ide.Workbench ActiveDocument="Assets/Level3Controls.cs">
    <Files>
      <File FileName="Assets/moveUp.cs" Line="142" Column="54" />
      <File FileName="Assets/Pantalla.cs" />
      <File FileName="Assets/Level2Recognition.cs" />
      <File FileName="Assets/Level3Recognition.cs" />
      <File FileName="Assets/startGame.cs" />
      <File FileName="Assets/controls.cs" />
      <File FileName="Assets/Level3Controls.cs" Line="262" Column="14" />
    </Files>
  </MonoDevelop.Ide.Workbench>
  <MonoDevelop.Ide.DebuggingService.PinnedWatches />
  <MonoDevelop.Ide.Workspace ActiveConfiguration="Debug" />
  <MonoDevelop.Ide.ItemProperties.Assembly-CSharp PreferredExecutionTarget="3e95302a-eac3-4468-877a-c7956b73bd5b" />
  <MonoDevelop.Ide.DebuggingService.Breakpoints>
    <BreakpointStore />
  </MonoDevelop.Ide.DebuggingService.Breakpoints>
  <MultiItemStartupConfigurations />
</Properties>